argon2_solver/__init__.py
argon2_solver/main.py
argon2_solver-1.0.2.dist-info/LICENSE
argon2_solver-1.0.2.dist-info/METADATA
argon2_solver-1.0.2.dist-info/WHEEL
argon2_solver-1.0.2.dist-info/entry_points.txt
argon2_solver-1.0.2.dist-info/top_level.txt
argon2_solver-1.0.2.dist-info/RECORD
