Metadata-Version: 2.1
Name: argon2-solver
Version: 1.0.2
Summary: A solver for Argon2-based challenges.
Home-page: https://github.com/Klez2003/argon2-solver
Author: Klez
Author-email: klez@cock.li
Classifier: Programming Language :: Python :: 3
Classifier: License :: OSI Approved :: MIT License
Classifier: Operating System :: OS Independent
Requires-Python: >=3.6
License-File: LICENSE
